[
  {
    "nomor": 1,
    "soalKe": "Kenapa Patrick gabut?",
    "nilai": 0,
    "sindrom": "a"
  },
  {
    "nomor": 2,
    "soalKe": "Kenapa Spongebob warnanya kuning?",
    "nilai": 0,
    "sindrom": "a"
  },
  {
    "nomor": 3,
    "soalKe": "Kenapa gary itu siput?",
    "nilai": 0,
    "sindrom": "a"
  },
  {
    "nomor": 4,
    "soalKe": "Kenapa tuan krab itu kepiting?",
    "nilai": 0,
    "sindrom": "a"
  },
  {
    "nomor": 5,
    "soalKe": "Kenapa squidward cumi2?",
    "nilai": 0,
    "sindrom": "a"
  },
  {
    "nomor": 6,
    "soalKe": "Kenapa sandy tupai?",
    "nilai": 0,
    "sindrom": "a"
  },
  {
    "nomor": 7,
    "soalKe": "Kenapa nyonya puff besar?",
    "nilai": 0,
    "sindrom": "a"
  },
  {
    "nomor": 8,
    "soalKe": "Kenapa plankton iseng?",
    "nilai": 0,
    "sindrom": "a"
  },
  {
    "nomor": 9,
    "soalKe": "Kenapa patrick bintang?",
    "nilai": 0,
    "sindrom": "a"
  },
  {
    "nomor": 10,
    "soalKe": "Kenapa tom and jerry?",
    "nilai": 0,
    "sindrom": "a"
  }
]
